{
  "generator-jhipster": {
    "applicationType": "monolith",
    "authenticationType": "jwt",
    "baseName": "IdempotencyAppPOC",
    "blueprints": [],
    "buildTool": "maven",
    "cacheProvider": "redis",
    "clientFramework": "vue",
    "clientPackageManager": "npm",
    "creationTimestamp": 1732117169132,
    "databaseType": "sql",
    "devDatabaseType": "h2Disk",
    "devServerPort": 9060,
    "enableHibernateCache": true,
    "enableSwaggerCodegen": false,
    "enableTranslation": true,
    "entities": ["Post"],
    "gitCompany": "",
    "jhiPrefix": "jhi",
    "jhipsterVersion": "8.7.1",
    "jwtSecretKey": "YTg3YmM2OGM0N2U5OTgzYzI5NjJkNzJjYTczNzM1NDk5ODk5MzgwYmMyZDVmZjM3YTg1NTRlMTA3MzkzZTNjZWQyMmM1NGI0ZTA4OTA1NDIxNDdiODJlNmQyNDViOTM1OWQ3ZjAwYTZjZjdiMzk1MWNiYjQxNzFhODQ1OTY2Yzk=",
    "languages": ["fr", "en"],
    "lastLiquibaseTimestamp": 1732123164000,
    "messageBroker": false,
    "nativeLanguage": "fr",
    "packageFolder": "com/df/myapp",
    "packageName": "com.df.myapp",
    "prodDatabaseType": "postgresql",
    "searchEngine": false,
    "serverPort": 8078,
    "serviceDiscoveryType": false,
    "testFrameworks": ["cucumber"],
    "useSass": true,
    "websocket": false,
    "withAdminUi": true
  }
}
